{
    "apl": 3,
    "authors": [
        "Casper Akto Kanstrup",
        "Martin Akto Kanstrup"
    ],
    "campaign": "Forgotten Realms",
    "code": "DC-POA-CONMAR-09",
    "date_created": "20210811",
    "full_title": "DC-PoA-CONMAR-09 That's a lot of Kobolds",
    "hours": 4,
    "level_range": null,
    "product_id": "DC-PoA-CONMAR-09-Thats-a-lot-of-Kobolds",
    "tiers": 1,
    "title": "DC-PoA-CONMAR-09 That's a lot of Kobolds",
    "url": "https://www.dmsguild.com/product/367396/DCPoACONMAR09-Thats-a-lot-of-Kobolds?filters=0_0_100057_0_0_0_0_0"
}