{
    "apl": null,
    "authors": [
        "Pierfrancesco Lucchetti"
    ],
    "campaign": [
        "Forgotten Realms"
    ],
    "code": "DDAL-DRW-INT-01",
    "date_created": "20221022",
    "full_title": "DDAL-DRW-INT-01 Big Problem Map Asstes",
    "hours": null,
    "level_range": "0",
    "product_id": "DDAL-DRW-INT-01-Big-Problem-Map-Asstes",
    "tiers": null,
    "title": "DDAL-DRW-INT-01 Big Problem Map Asstes",
    "url": "https://www.dmsguild.com/product/414282/DDALDRWINT01-Big-Problem-Map-Asstes"
}