{
    "apl": 3,
    "authors": [
        "Ma'at Crook"
    ],
    "campaign": "Forgotten Realms",
    "code": "WBW-DC-MC-01",
    "date_created": "20220831",
    "full_title": "WBW-DC-MC-01 Memento Motus: S\u00e9ance for the Lost",
    "hours": 4,
    "level_range": null,
    "product_id": "WBW-DC-MC-01-Memento-Motus--S\u00e9ance-for-the-Lost",
    "tiers": null,
    "title": "Memento Motus S\u00e9ance for the Lost",
    "url": "https://www.dmsguild.com/product/408609/WBWDCMC01-Memento-Motus-Seance-for-the-Lost?filters=45470_0_0_0_0_0"
}